CHANGES.txt
MANIFEST.in
README.txt
setup.py
isotoma/__init__.py
isotoma.recipe.zeo.egg-info/PKG-INFO
isotoma.recipe.zeo.egg-info/SOURCES.txt
isotoma.recipe.zeo.egg-info/dependency_links.txt
isotoma.recipe.zeo.egg-info/entry_points.txt
isotoma.recipe.zeo.egg-info/namespace_packages.txt
isotoma.recipe.zeo.egg-info/not-zip-safe
isotoma.recipe.zeo.egg-info/requires.txt
isotoma.recipe.zeo.egg-info/top_level.txt
isotoma/recipe/__init__.py
isotoma/recipe/zeo/__init__.py
isotoma/recipe/zeo/ctl.py
isotoma/recipe/zeo/pack.py
isotoma/recipe/zeo/recipe.py
isotoma/recipe/zeo/tests/__init__.py
isotoma/recipe/zeo/tests/test_docs.py