Metadata-Version: 1.0
Name: isotoma.recipe.zeo
Version: 2.0.4
Summary: Custom version of plone.recipe.zeoserver
Home-page: http://pypi.python.org/pypi/isotoma.recipe.zeo
Author: UNKNOWN
Author-email: UNKNOWN
License: ZPL 2.1
Keywords: zope2 zeo zodb buildout
Platform: UNKNOWN
Classifier: License :: OSI Approved :: Zope Public License
Classifier: Framework :: Buildout
Classifier: Framework :: Zope2
Classifier: Programming Language :: Python
